pitchplots/__init__.py
pitchplots/functions.py
pitchplots/modified_musicxml_parser.py
pitchplots/parser.py
pitchplots/reader.py
pitchplots/static.py
pitchplots/data/data_example.mxl
pitchplots-1.4.2.dist-info/LICENCE.txt
pitchplots-1.4.2.dist-info/METADATA
pitchplots-1.4.2.dist-info/WHEEL
pitchplots-1.4.2.dist-info/top_level.txt
pitchplots-1.4.2.dist-info/RECORD
