Metadata-Version: 2.1
Name: pitchplots
Version: 1.4.2
Summary: A package containing representation tools for musical purposes
Home-page: https://github.com/DCMLab/pitchplots
Author: Fabian Moss
Author-email: fabian.moss@epfl.ch
License: UNKNOWN
Platform: UNKNOWN
Classifier: Programming Language :: Python :: 3
Classifier: License :: OSI Approved :: MIT License
Classifier: Operating System :: OS Independent
Requires-Dist: matplotlib (>=3.0.1)
Requires-Dist: pandas (>=0.23.4)
Requires-Dist: numpy (>=1.15.3)
